pyntelope/__init__.py
pyntelope/_version.py
pyntelope/exc.py
pyntelope/net.py
pyntelope/transaction.py
pyntelope/types/__init__.py
pyntelope/types/base.py
pyntelope/types/compostes.py
pyntelope/types/primitives.py
pyntelope/utils.py
pyntelope-0.8.6.dist-info/LICENSE
pyntelope-0.8.6.dist-info/METADATA
pyntelope-0.8.6.dist-info/WHEEL
pyntelope-0.8.6.dist-info/RECORD
