Metadata-Version: 2.1
Name: pyntelope
Version: 0.8.6
Summary: Interact with Antelope blockchains
Home-page: https://github.com/FACINGS/pyntelope
Author: Team
Author-email: pyntelope@facings.io
Requires-Python: >=3.8,<4.0
Classifier: Programming Language :: Python :: 3
Classifier: Programming Language :: Python :: 3.8
Classifier: Programming Language :: Python :: 3.9
Classifier: Programming Language :: Python :: 3.10
Classifier: Programming Language :: Python :: 3.11
Requires-Dist: base58 (>=2.1.1,<3.0.0)
Requires-Dist: httpx (>=0.22)
Requires-Dist: pycryptodome (>=3.15.0,<4.0.0)
Requires-Dist: pydantic (>=1.9.0,<2.0.0)
